AUTHORS
CONFIGURATION.md
ChangeLog
LICENSE
MANIFEST.in
README.md
requirements.txt
setup.py
bingo/__init__.py
bingo/admin.py
bingo/context_processors.py
bingo/forms.py
bingo/generic.py
bingo/image.py
bingo/models.py
bingo/tests.py
bingo/times.py
bingo/urls.py
bingo/views.py
bingo/bin/django-bingo-serversent.py
bingo/locale/de/LC_MESSAGES/django.po
bingo/static/bingo/background.png
bingo/static/bingo/style.css
bingo/static/bingo/js/bingo.js
bingo/static/bingo/js/board_list.js
bingo/static/bingo/js/titletext.js
bingo/static/bingo/themes/dark.css
bingo/static/bingo/themes/light.css
bingo/static/bingo/themes/dark/background.png
bingo/templates/bingo/base.html
bingo/templates/bingo/bingo.html
bingo/templates/bingo/board_list.html
bingo/templates/bingo/forms.html
bingo/templates/bingo/game.html
bingo/templates/bingo/game_list.html
bingo/templates/bingo/game_rating.html
bingo/templates/bingo/main.html
bingo/templates/bingo/profile.html
bingo/templates/bingo/rating_display.html
bingo/templates/bingo/reclaim_board.html
bingo/templates/bingo/stats.html
bingo/templates/bingo/theme_chooser.html
bingo/templates/bingo/vote_form.html
bingo/templates/registration/login.html
bingo/templates/registration/logout.html
bingo/templates/registration/registration_form.html
django_bingo.egg-info/PKG-INFO
django_bingo.egg-info/SOURCES.txt
django_bingo.egg-info/dependency_links.txt
django_bingo.egg-info/requires.txt
django_bingo.egg-info/top_level.txt