Metadata-Version: 1.1
Name: django-bingo
Version: 1.6.0
Summary: Bingo
Home-page: https://github.com/allo-/django-bingo
Author: Alexander Schier
Author-email: allo@laxu.de
License: UNKNOWN
Platform: UNKNOWN
Classifier: Framework :: Django
Classifier: Topic :: Games/Entertainment :: Board Games
Classifier: License :: OSI Approved :: GNU Affero General Public License v3
Classifier: Operating System :: OS Independent
Classifier: Programming Language :: Python
